fisea/__init__.py
fisea/_extension.cpp
fisea/tensor/__init__.py
fisea/tensor/_extension.cpp
fisea/functional/testfn.cuh
fisea/functional/_cpp_extension.cpython-312-darwin.so
fisea/functional/testfn.cpp
fisea/functional/testfn.cu
fisea/functional/__init__.py
fisea/functional/_extension.cpp
fisea/functional/testfn.h
fisea-0.0.1.dist-info/RECORD
fisea-0.0.1.dist-info/WHEEL
fisea-0.0.1.dist-info/METADATA
