Metadata-Version: 2.1
Name: fisea
Version: 0.0.1
Summary: A mini library simulate the behavior of torch
Author-Email: Fish Chen <me@email.com>, Season Lo <chlo-mo@outlook.com>
Classifier: Development Status :: 4 - Beta
Classifier: License :: OSI Approved :: MIT License
Classifier: Programming Language :: Python :: 3 :: Only
Classifier: Programming Language :: Python :: 3.9
Classifier: Programming Language :: Python :: 3.10
Classifier: Programming Language :: Python :: 3.11
Classifier: Programming Language :: Python :: 3.12
Requires-Python: >=3.9
Provides-Extra: test
Requires-Dist: pytest; extra == "test"
